{"chunk_definitions":[{"row":10,"row_count":1,"visible":true,"expansion_state":0,"options":{"engine":"r","label":"unnamed-chunk-2"},"document_id":"D6FA7982","chunk_id":"cxseyl86mnevd","chunk_label":"unnamed-chunk-1"},{"row":23,"row_count":1,"visible":true,"expansion_state":0,"options":{"engine":"r","label":"unnamed-chunk-22"},"document_id":"D6FA7982","chunk_id":"cemzye86d94eh","chunk_label":"unnamed-chunk-2"},{"row":29,"row_count":1,"visible":true,"expansion_state":0,"options":{"engine":"r","label":"unnamed-chunk-27"},"document_id":"D6FA7982","chunk_id":"co4ecss66jh5t","chunk_label":"unnamed-chunk-3"},{"row":35,"row_count":1,"visible":true,"expansion_state":0,"options":{"engine":"r","label":"unnamed-chunk-28"},"document_id":"D6FA7982","chunk_id":"crqb72bbhe76a","chunk_label":"unnamed-chunk-4"},{"row":41,"row_count":1,"visible":true,"expansion_state":0,"options":{"engine":"r","label":"unnamed-chunk-29"},"document_id":"D6FA7982","chunk_id":"ckp4in3n719xl","chunk_label":"unnamed-chunk-5"},{"row":50,"row_count":1,"visible":true,"expansion_state":0,"options":{"engine":"r","label":"unnamed-chunk-31"},"document_id":"D6FA7982","chunk_id":"cei7at3lpfjil","chunk_label":"unnamed-chunk-6"}],"doc_write_time":1667458869,"chunk_rendered_width":446}